oracle_csv_creator/__init__.py
oracle_csv_creator/cli.py
oracle_csv_creator/core.py
oracle_csv_creator-0.1.2.dist-info/METADATA
oracle_csv_creator-0.1.2.dist-info/WHEEL
oracle_csv_creator-0.1.2.dist-info/entry_points.txt
oracle_csv_creator-0.1.2.dist-info/licenses/LICENSE
oracle_csv_creator-0.1.2.dist-info/RECORD
