Metadata-Version: 2.4
Name: oracle-csv-creator
Version: 0.1.2
Summary: Parallel Oracle table to CSV writer using rowid ranges and optional consistency.
Project-URL: Homepage, https://pypi.org/project/oracle-csv-creator/
Project-URL: Repository, https://example.com/your-repo
Project-URL: Issues, https://example.com/your-repo/issues
Author-email: Your Name <you@example.com>
License: MIT License
License-File: LICENSE
Keywords: csv,database,etl,export,oracle,parallel,rowid
Classifier: License :: OSI Approved :: MIT License
Classifier: Operating System :: OS Independent
Classifier: Programming Language :: Python :: 3
Classifier: Topic :: Database
Classifier: Topic :: Utilities
Requires-Python: >=3.9
Requires-Dist: oracledb>=2.0.0
